{"1": {"status": "Disabled"}, "2": {"status": "Disabled"}, "3": {"status": "Disabled"}, "4": {"status": "Disabled"}, "5": {"status": "Disabled"}, "6": {"status": "Disabled"}, "7": {"status": "Disabled"}, "8": {"status": "Disabled"}, "9": {"status": "Disabled"}, "10": {"status": "Disabled"}, "11": {"status": "Disabled"}, "12": {"status": "Disabled"}, "13": {"status": "Available", "occupiedBy": "", "occupiedTime": ""}, "14": {"status": "Disabled"}, "15": {"status": "Disabled"}, "16": {"status": "Disabled"}, "17": {"status": "Disabled"}, "18": {"status": "Disabled"}, "19": {"status": "Available", "occupiedBy": "", "occupiedTime": ""}, "20": {"status": "Disabled"}, "21": {"status": "Available", "occupiedBy": "", "occupiedTime": ""}, "22": {"status": "Disabled"}, "23": {"status": "Disabled"}, "24": {"status": "Available", "occupiedBy": "", "occupiedTime": ""}, "25": {"status": "Disabled"}, "26": {"status": "Disabled"}, "27": {"status": "Available", "occupiedBy": "", "occupiedTime": ""}, "28": {"status": "Disabled"}, "29": {"status": "Disabled"}, "30": {"status": "Available", "occupiedBy": "", "occupiedTime": ""}, "31": {"status": "Disabled"}, "32": {"status": "Disabled"}, "33": {"status": "Disabled"}, "34": {"status": "Disabled"}, "35": {"status": "Disabled"}, "36": {"status": "Disabled"}, "37": {"status": "Disabled"}, "38": {"status": "Available", "occupiedBy": "", "occupiedTime": ""}, "39": {"status": "Disabled"}, "40": {"status": "Disabled"}, "41": {"status": "Available", "occupiedBy": "", "occupiedTime": ""}, "42": {"status": "Available", "occupiedBy": "", "occupiedTime": ""}, "43": {"status": "Available", "occupiedBy": "", "occupiedTime": ""}, "44": {"status": "Available", "occupiedBy": "", "occupiedTime": ""}, "45": {"status": "Disabled"}, "46": {"status": "Disabled"}, "47": {"status": "Available", "occupiedBy": "", "occupiedTime": ""}, "48": {"status": "Available", "occupiedBy": "", "occupiedTime": ""}, "49": {"status": "Disabled"}, "50": {"status": "Available", "occupiedBy": "", "occupiedTime": ""}, "51": {"status": "Disabled"}, "52": {"status": "Disabled"}, "53": {"status": "Disabled"}, "54": {"status": "Disabled"}, "55": {"status": "Available", "occupiedBy": "", "occupiedTime": ""}, "56": {"status": "Available", "occupiedBy": "", "occupiedTime": ""}, "57": {"status": "Available", "occupiedBy": "", "occupiedTime": ""}, "58": {"status": "Disabled"}, "59": {"status": "Available", "occupiedBy": "", "occupiedTime": ""}, "60": {"status": "Disabled"}, "61": {"status": "Disabled"}, "62": {"status": "Available", "occupiedBy": "", "occupiedTime": ""}, "63": {"status": "Disabled"}, "64": {"status": "Disabled"}, "65": {"status": "Available", "occupiedBy": "", "occupiedTime": ""}, "66": {"status": "Available", "occupiedBy": "", "occupiedTime": ""}, "67": {"status": "Available", "occupiedBy": "", "occupiedTime": ""}, "68": {"status": "Available", "occupiedBy": "", "occupiedTime": ""}, "69": {"status": "Disabled"}, "70": {"status": "Disabled"}, "71": {"status": "Disabled"}, "72": {"status": "Available", "occupiedBy": "", "occupiedTime": ""}, "73": {"status": "Available", "occupiedBy": "", "occupiedTime": ""}, "74": {"status": "Disabled"}, "75": {"status": "Available", "occupiedBy": "", "occupiedTime": ""}, "76": {"status": "Available", "occupiedBy": "", "occupiedTime": ""}, "77": {"status": "Disabled"}, "78": {"status": "Disabled"}, "79": {"status": "Available", "occupiedBy": "", "occupiedTime": ""}, "80": {"status": "Available", "occupiedBy": "", "occupiedTime": ""}, "81": {"status": "Disabled"}, "82": {"status": "Disabled"}, "83": {"status": "Disabled"}, "84": {"status": "Available", "occupiedBy": "", "occupiedTime": ""}, "85": {"status": "Available", "occupiedBy": "", "occupiedTime": ""}, "86": {"status": "Disabled"}, "87": {"status": "Available", "occupiedBy": "", "occupiedTime": ""}, "88": {"status": "Disabled"}, "89": {"status": "Available", "occupiedBy": "", "occupiedTime": ""}, "90": {"status": "Available", "occupiedBy": "", "occupiedTime": ""}, "91": {"status": "Disabled"}, "92": {"status": "Disabled"}, "93": {"status": "Available", "occupiedBy": "", "occupiedTime": ""}, "94": {"status": "Disabled"}, "95": {"status": "Available", "occupiedBy": "", "occupiedTime": ""}}